harborclient_light/__init__.py
harborclient_light/harborclient.py
harborclient_light/test_harborclient.py
harbor_py_light-2.1.2.dist-info/LICENSE
harbor_py_light-2.1.2.dist-info/METADATA
harbor_py_light-2.1.2.dist-info/WHEEL
harbor_py_light-2.1.2.dist-info/top_level.txt
harbor_py_light-2.1.2.dist-info/RECORD
