Metadata-Version: 2.1
Name: harbor-py-light
Version: 2.1.2
Summary: The reborn Harbor Python SDK
Home-page: https://github.com/fedor-chemashkin/harbor-py-light
Author: fedos
Author-email: fedor.chemashkin@gmail.com
License: Apache Software
Keywords: harbor python client sdk docker registry distribution
Platform: UNKNOWN
Classifier: Development Status :: 5 - Production/Stable
Classifier: Intended Audience :: Developers
Classifier: Topic :: Software Development :: Build Tools
Classifier: License :: OSI Approved :: Apache Software License
Classifier: Programming Language :: Python :: 2
Classifier: Programming Language :: Python :: 2.6
Classifier: Programming Language :: Python :: 2.7
Classifier: Programming Language :: Python :: 3
Classifier: Programming Language :: Python :: 3.3
Classifier: Programming Language :: Python :: 3.4
Classifier: Programming Language :: Python :: 3.5
Classifier: Programming Language :: Python :: 3.6
